defect_detection/__init__.py
defect_detection/deep_AE.py
defect_detection/filtering.py
defect_detection/functions.py
defect_detection/preprocessing.py
defect_detection/training.py
defect_detection/version.py
defect_detection-0.4.4.dist-info/licenses/LICENSE
defect_detection-0.4.4.dist-info/METADATA
defect_detection-0.4.4.dist-info/WHEEL
defect_detection-0.4.4.dist-info/top_level.txt
defect_detection-0.4.4.dist-info/RECORD
