Metadata-Version: 2.4
Name: defect_detection
Version: 0.4.4
Summary: API for defect detection in PCB and other components.
Author-email: Louis Vaslin <lovaslin@post.kek.jp>
Maintainer-email: Louis Vaslin <lovaslin@post.kek.jp>
License: BSD 3-Clause License
Project-URL: Documentation, https://github.com/lovaslin/defect_detection
Project-URL: Homepage, https://github.com/lovaslin/defect_detection
Project-URL: Bug Tracker, https://github.com/lovaslin/defect_detection/issues
Project-URL: Source, https://github.com/lovaslin/defect_detection
Classifier: Development Status :: 1 - Planning
Classifier: Intended Audience :: Developers
Classifier: Intended Audience :: Science/Research
Classifier: License :: OSI Approved :: BSD License
Classifier: Operating System :: OS Independent
Classifier: Programming Language :: Python
Classifier: Programming Language :: Python :: 3
Classifier: Programming Language :: Python :: 3 :: Only
Classifier: Programming Language :: Python :: 3.7
Classifier: Programming Language :: Python :: 3.8
Classifier: Programming Language :: Python :: 3.9
Classifier: Programming Language :: Python :: 3.10
Classifier: Programming Language :: Python :: 3.11
Classifier: Topic :: Scientific/Engineering
Requires-Python: >=3.7
License-File: LICENSE
Requires-Dist: opencv-python-headless
Requires-Dist: numpy
Requires-Dist: torch
Requires-Dist: scikit-learn
Dynamic: license-file
